srl/__init__.py
srl/version.py
srl/algorithms/__init__.py
srl/algorithms/dynaq.py
srl/algorithms/go_dynaq.py
srl/algorithms/mcts.py
srl/algorithms/ql.py
srl/algorithms/ql_agent57.py
srl/algorithms/search_dynaq.py
srl/algorithms/vanilla_policy.py
srl/algorithms/agent57/__init__.py
srl/algorithms/agent57/agent57.py
srl/algorithms/agent57/model_tf.py
srl/algorithms/agent57/model_torch.py
srl/algorithms/agent57_light/__init__.py
srl/algorithms/agent57_light/agent57_light.py
srl/algorithms/agent57_light/model_tf.py
srl/algorithms/agent57_light/model_torch.py
srl/algorithms/alphazero/__init__.py
srl/algorithms/alphazero/alphazero.py
srl/algorithms/alphazero/config.py
srl/algorithms/c51/__init__.py
srl/algorithms/c51/c51.py
srl/algorithms/c51/config.py
srl/algorithms/ddpg/__init__.py
srl/algorithms/ddpg/config.py
srl/algorithms/ddpg/ddpg.py
srl/algorithms/diamond/__init__.py
srl/algorithms/diamond/config.py
srl/algorithms/diamond/memory.py
srl/algorithms/diamond/model_actor_critic.py
srl/algorithms/diamond/model_denoiser.py
srl/algorithms/diamond/model_reward_end.py
srl/algorithms/diamond/model_sampler.py
srl/algorithms/diamond/model_unet.py
srl/algorithms/diamond/parameter.py
srl/algorithms/diamond/trainer.py
srl/algorithms/diamond/worker.py
srl/algorithms/dqn/__init__.py
srl/algorithms/dqn/dqn.py
srl/algorithms/dqn/model_tf.py
srl/algorithms/dqn/model_torch.py
srl/algorithms/dqn_not/__init__.py
srl/algorithms/dqn_not/config.py
srl/algorithms/dqn_not/parameter.py
srl/algorithms/dqn_not/trainer.py
srl/algorithms/dqn_not/worker.py
srl/algorithms/dreamer_v3/__init__.py
srl/algorithms/dreamer_v3/config.py
srl/algorithms/dreamer_v3/dreamer_v3.py
srl/algorithms/dreamer_v3/model.py
srl/algorithms/efficient_zero_v2/__init__.py
srl/algorithms/efficient_zero_v2/config.py
srl/algorithms/efficient_zero_v2/mcts.py
srl/algorithms/efficient_zero_v2/memory.py
srl/algorithms/efficient_zero_v2/model.py
srl/algorithms/efficient_zero_v2/parameter.py
srl_framework-1.4.4.dist-info/licenses/LICENSE
srl_framework-1.4.4.dist-info/METADATA
srl_framework-1.4.4.dist-info/WHEEL
srl_framework-1.4.4.dist-info/top_level.txt
srl_framework-1.4.4.dist-info/RECORD
