Metadata-Version: 2.4
Name: srl-framework
Version: 1.4.4
Summary: Simple distributed reinforcement learning framework
Author-email: poco <pocopococpp198@gmail.com>
License-Expression: MIT
Project-URL: Homepage, https://pocokhc.github.io/simple_distributed_rl/
Project-URL: Repository, https://github.com/pocokhc/simple_distributed_rl
Classifier: Development Status :: 4 - Beta
Classifier: Programming Language :: Python
Classifier: Programming Language :: Python :: 3
Classifier: Programming Language :: Python :: 3.9
Classifier: Programming Language :: Python :: 3.10
Classifier: Programming Language :: Python :: 3.11
Classifier: Programming Language :: Python :: 3.12
Classifier: Programming Language :: Python :: 3.13
Requires-Python: >=3.9
License-File: LICENSE
Requires-Dist: numpy
Requires-Dist: opencv-python
Requires-Dist: Pillow
Requires-Dist: pygame
Requires-Dist: pyyaml
Provides-Extra: full
Requires-Dist: gymnasium; extra == "full"
Requires-Dist: matplotlib; extra == "full"
Requires-Dist: pandas; extra == "full"
Requires-Dist: psutil; extra == "full"
Requires-Dist: pynvml; extra == "full"
Requires-Dist: redis; extra == "full"
Requires-Dist: mlflow; extra == "full"
Requires-Dist: pybind11; extra == "full"
Requires-Dist: setuptools; extra == "full"
Provides-Extra: dev
Requires-Dist: gymnasium; extra == "dev"
Requires-Dist: matplotlib; extra == "dev"
Requires-Dist: pandas; extra == "dev"
Requires-Dist: psutil; extra == "dev"
Requires-Dist: pynvml; extra == "dev"
Requires-Dist: redis; extra == "dev"
Requires-Dist: mlflow; extra == "dev"
Requires-Dist: pybind11; extra == "dev"
Requires-Dist: setuptools; extra == "dev"
Requires-Dist: pytest; extra == "dev"
Requires-Dist: pytest-mock; extra == "dev"
Requires-Dist: pytest-timeout; extra == "dev"
Dynamic: license-file
